Metadata-Version: 1.0
Name: bikesh
Version: 0.7
Summary: Bikesh M
Home-page: UNKNOWN
Author: Bikesh M
Author-email: bikeshm@gmail.com
License: MIT
Platform: UNKNOWN
